__init__.py
markdown_url_validator.py
markdown_url_validator-1.0.0.dist-info/LICENSE
markdown_url_validator-1.0.0.dist-info/METADATA
markdown_url_validator-1.0.0.dist-info/WHEEL
markdown_url_validator-1.0.0.dist-info/top_level.txt
markdown_url_validator-1.0.0.dist-info/RECORD
