Metadata-Version: 2.1
Name: markdown-url-validator
Version: 1.0.0
Summary: This package can be used to validate URLs present in markdown content. It checks the status of the url and requires an internet connection to work.
Author-email: Akshat Jaimini <destrex271@gmail.com>
Project-URL: Homepage, https://github.com/destrex271/markdown_url_validator
Project-URL: Bug Tracker, https://github.com/destrex271/markdown_url_validator/issues
Classifier: Programming Language :: Python :: 3
Classifier: License :: OSI Approved :: MIT License
Classifier: Operating System :: OS Independent
Requires-Python: >=3.7
License-File: LICENSE
